MANIFEST.in
README.rst
buildout.cfg
resumelb.spec
rpm.cfg
setup.py
simul_setup.py
tree.text
src/zc/__init__.py
src/zc.resumelb.egg-info/PKG-INFO
src/zc.resumelb.egg-info/SOURCES.txt
src/zc.resumelb.egg-info/dependency_links.txt
src/zc.resumelb.egg-info/entry_points.txt
src/zc.resumelb.egg-info/namespace_packages.txt
src/zc.resumelb.egg-info/not-zip-safe
src/zc.resumelb.egg-info/requires.txt
src/zc.resumelb.egg-info/top_level.txt
src/zc/resumelb/__init__.py
src/zc/resumelb/bufferedqueue.test
src/zc/resumelb/bytesizedqueue.test
src/zc/resumelb/classlesspool.py
src/zc/resumelb/classlesspool.test
src/zc/resumelb/interfaces.py
src/zc/resumelb/lb.py
src/zc/resumelb/lb.test
src/zc/resumelb/nagios.py
src/zc/resumelb/nagios.rst
src/zc/resumelb/nagiosfauxstatus.py
src/zc/resumelb/pool.test
src/zc/resumelb/protocol.txt
src/zc/resumelb/simul.py
src/zc/resumelb/single_version.test
src/zc/resumelb/tests.py
src/zc/resumelb/util.py
src/zc/resumelb/worker.py
src/zc/resumelb/worker.test
src/zc/resumelb/zk.py
src/zc/resumelb/zk.test