Metadata-Version: 1.0
Name: zc.resumelb
Version: 1.0.2
Summary: Résumé-based WSGI load balancer
Home-page: UNKNOWN
Author: Jim Fulton
Author-email: jim@zope.com
License: ZPL 2.1
Platform: UNKNOWN
